{"kind":"identitytoolkit#DownloadAccountResponse","users":[{"localId":"F7vOaGFcNzdvPNkW3va55Lgyvogo","lastLoginAt":"1741383688483","emailVerified":false,"email":"michael.scott@theoffice.com.br","salt":"fakeSaltzrgVNGxGCJZuiURQO1Mr","passwordHash":"fakeHash:salt=fakeSaltzrgVNGxGCJZuiURQO1Mr:password=Testando4","passwordUpdatedAt":1741383688483,"validSince":"1741383688","createdAt":"1741383688483","providerUserInfo":[{"providerId":"password","email":"michael.scott@theoffice.com.br","federatedId":"michael.scott@theoffice.com.br","rawId":"michael.scott@theoffice.com.br"}],"lastRefreshAt":"2025-03-07T21:41:28.483Z"}]}