{"kind":"identitytoolkit#DownloadAccountResponse","users":[{"localId":"LUJHrvmagwi6QcMFklFEmq5xbuUp","createdAt":"1741966030359","lastLoginAt":"1741966030359","passwordHash":"fakeHash:salt=fakeSalt02wdsmIKTg4H4rsOEcn6:password=Testando4","salt":"fakeSalt02wdsmIKTg4H4rsOEcn6","passwordUpdatedAt":1744926270294,"providerUserInfo":[{"providerId":"password","email":"michael.scott@theoffice.com","federatedId":"michael.scott@theoffice.com","rawId":"michael.scott@theoffice.com"}],"validSince":"1744926270","email":"michael.scott@theoffice.com","emailVerified":false,"disabled":false},{"localId":"i0JY9p8r5MtOADv2kjQ8rTN8yUDo","createdAt":"1741966390207","lastLoginAt":"1744928592621","passwordHash":"fakeHash:salt=fakeSalt3yxwj7w1Fc2JrwI4F156:password=Testando4","salt":"fakeSalt3yxwj7w1Fc2JrwI4F156","passwordUpdatedAt":1744926270294,"providerUserInfo":[{"providerId":"password","email":"jim.halpert@theoffice.com","federatedId":"jim.halpert@theoffice.com","rawId":"jim.halpert@theoffice.com"}],"validSince":"1744926270","email":"jim.halpert@theoffice.com","emailVerified":false,"disabled":false,"lastRefreshAt":"2025-04-17T22:23:12.621Z"}]}